LICENSE
MANIFEST.in
README.rst
helga_ignore.py
setup.py
helga_ignore.egg-info/PKG-INFO
helga_ignore.egg-info/SOURCES.txt
helga_ignore.egg-info/dependency_links.txt
helga_ignore.egg-info/entry_points.txt
helga_ignore.egg-info/top_level.txt
helga_ignore.egg-info/zip-safe